doc/Makefile
doc/bibfile.bib
doc/conf.py
doc/docutils.conf
doc/index.rst
doc/requirements.txt
doc/robots.txt
doc/_static/draw_mpl/draw_mpl_examples.py
doc/_static/drawer/mpldrawer_examples.py
doc/_static/pulse/make_pulse_images.py
doc/_static/style/style_examples.py
doc/_static/tape_mpl/tape_mpl_examples.py
pennylane/__init__.py
pennylane/_deprecated_observable.py
pennylane/_grad.py
pennylane/_version.py
pennylane/about.py
pennylane/allocation.py
pennylane/boolean_fn.py
pennylane/circuit_graph.py
pennylane/configuration.py
pennylane/exceptions.py
pennylane/operation.py
pennylane/queuing.py
pennylane/registers.py
pennylane/typing.py
pennylane/wires.py
pennylane/bose/__init__.py
pennylane/bose/bosonic.py
pennylane/bose/bosonic_mapping.py
pennylane/capture/__init__.py
pennylane/capture/base_interpreter.py
pennylane/capture/capture_meta.py
pennylane/capture/custom_primitives.py
pennylane/capture/dynamic_shapes.py
pennylane/capture/expand_transforms.py
pennylane/capture/flatfn.py
pennylane/capture/make_plxpr.py
pennylane/capture/primitives.py
pennylane/capture/switches.py
pennylane/capture/autograph/__init__.py
pennylane/capture/autograph/ag_primitives.py
pennylane/capture/autograph/transformer.py
pennylane/compiler/__init__.py
pennylane/compiler/compiler.py
pennylane/compiler/qjit_api.py
pennylane/compiler/python_compiler/__init__.py
pennylane/compiler/python_compiler/compiler.py
pennylane/compiler/python_compiler/jax_utils.py
pennylane/compiler/python_compiler/quantum_dialect.py
pennylane/compiler/python_compiler/transforms/__init__.py
pennylane/compiler/python_compiler/transforms/cancel_inverses.py
pennylane/compiler/python_compiler/transforms/merge_rotations.py
pennylane/compiler/python_compiler/transforms/api/__init__.py
pennylane/compiler/python_compiler/transforms/api/apply_transform_sequence.py
pennylane/compiler/python_compiler/transforms/api/compiler_transform.py
pennylane/compiler/python_compiler/transforms/api/transform_interpreter.py
pennylane-0.42.0.dist-info/licenses/LICENSE
pennylane-0.42.0.dist-info/METADATA
pennylane-0.42.0.dist-info/WHEEL
pennylane-0.42.0.dist-info/entry_points.txt
pennylane-0.42.0.dist-info/top_level.txt
pennylane-0.42.0.dist-info/RECORD
