Metadata-Version: 2.4
Name: pennylane
Version: 0.42.0
Summary: PennyLane is a cross-platform Python library for quantum computing, quantum machine learning, and quantum chemistry. Train a quantum computer the same way as a neural network.
Maintainer-email: "Xanadu Quantum Technologies Inc." <software@xanadu.ai>
License-Expression: Apache-2.0
Project-URL: repository, https://github.com/PennyLaneAI/pennylane
Classifier: Development Status :: 4 - Beta
Classifier: Environment :: Console
Classifier: Intended Audience :: Science/Research
Classifier: Natural Language :: English
Classifier: Operating System :: POSIX
Classifier: Operating System :: MacOS :: MacOS X
Classifier: Operating System :: POSIX :: Linux
Classifier: Operating System :: Microsoft :: Windows
Classifier: Programming Language :: Python
Classifier: Programming Language :: Python :: 3
Classifier: Programming Language :: Python :: 3.10
Classifier: Programming Language :: Python :: 3.11
Classifier: Programming Language :: Python :: 3.12
Classifier: Programming Language :: Python :: 3 :: Only
Classifier: Topic :: Scientific/Engineering :: Physics
Requires-Python: >=3.10
License-File: LICENSE
Requires-Dist: scipy
Requires-Dist: networkx
Requires-Dist: rustworkx>=0.14.0
Requires-Dist: autograd
Requires-Dist: appdirs
Requires-Dist: autoray>=0.6.11
Requires-Dist: cachetools
Requires-Dist: pennylane-lightning>=0.42
Requires-Dist: requests
Requires-Dist: tomlkit
Requires-Dist: typing_extensions
Requires-Dist: packaging
Requires-Dist: diastatic-malt
Requires-Dist: numpy
Provides-Extra: kernels
Requires-Dist: cvxpy; extra == "kernels"
Requires-Dist: cvxopt; extra == "kernels"
Dynamic: license-file
